rackspace_auth_neutronclientext
