Metadata-Version: 1.1
Name: rackspace-auth-neutronclientext
Version: 1.4
Summary: Rackspace Auth Plugin for OpenStack Neutron Clients.
Home-page: https://github.com/rackerlabs/rackspace-auth-neutronclientext
Author: Rackspace
Author-email: neutron-requests@lists.rackspace.com
License: Apache License, Version 2.0
Platform: UNKNOWN
Classifier: Development Status :: 5 - Production/Stable
Classifier: Environment :: Console
Classifier: Intended Audience :: Developers
Classifier: Intended Audience :: Information Technology
Classifier: License :: OSI Approved :: Apache Software License
Classifier: Operating System :: OS Independent
Classifier: Environment :: OpenStack
Classifier: Programming Language :: Python
